metricsfirst/__init__.py
metricsfirst/async_client.py
metricsfirst/client.py
metricsfirst/py.typed
metricsfirst/types.py
metricsfirst-0.1.8.dist-info/METADATA
metricsfirst-0.1.8.dist-info/WHEEL
metricsfirst-0.1.8.dist-info/licenses/LICENSE
metricsfirst-0.1.8.dist-info/RECORD
