Metadata-Version: 2.4
Name: metricsfirst
Version: 0.1.8
Summary: MetricsFirst SDK for Python - Analytics for Telegram bots
Project-URL: Homepage, https://metricsfirst.com
Project-URL: Documentation, https://docs.metricsfirst.com/python
Project-URL: Repository, https://github.com/metricsfirst/metricsfirst-python
Project-URL: Changelog, https://github.com/metricsfirst/metricsfirst-python/blob/main/CHANGELOG.md
Author-email: MetricsFirst <support@metricsfirst.com>
License-Expression: MIT
License-File: LICENSE
Keywords: analytics,bot,metrics,metricsfirst,telegram,tracking
Classifier: Development Status :: 4 - Beta
Classifier: Framework :: AsyncIO
Classifier: Intended Audience :: Developers
Classifier: License :: OSI Approved :: MIT License
Classifier: Operating System :: OS Independent
Classifier: Programming Language :: Python :: 3
Classifier: Programming Language :: Python :: 3.8
Classifier: Programming Language :: Python :: 3.9
Classifier: Programming Language :: Python :: 3.10
Classifier: Programming Language :: Python :: 3.11
Classifier: Programming Language :: Python :: 3.12
Classifier: Topic :: Software Development :: Libraries :: Python Modules
Requires-Python: >=3.8
Provides-Extra: async
Requires-Dist: aiohttp>=3.8.0; extra == 'async'
Provides-Extra: dev
Requires-Dist: aiohttp>=3.8.0; extra == 'dev'
Requires-Dist: black>=23.0.0; extra == 'dev'
Requires-Dist: mypy>=1.0.0; extra == 'dev'
Requires-Dist: pytest-asyncio>=0.20.0; extra == 'dev'
Requires-Dist: pytest>=7.0.0; extra == 'dev'
Requires-Dist: ruff>=0.1.0; extra == 'dev'
